{
  "lang":"en",
  "name":"pipeline",
  "version":"0.0.0",
  "spacy_version":">=3.5.3,<3.6.0",
  "description":"",
  "author":"",
  "email":"",
  "url":"",
  "license":"",
  "spacy_git_version":"Unknown",
  "vectors":{
    "width":0,
    "vectors":0,
    "keys":0,
    "name":null,
    "mode":"default"
  },
  "labels":{
    "transformer":[

    ],
    "ner":[
      "Degree",
      "Designation",
      "Years"
    ]
  },
  "pipeline":[
    "transformer",
    "ner"
  ],
  "components":[
    "transformer",
    "ner"
  ],
  "disabled":[

  ],
  "performance":{
    "ents_f":0.9728285078,
    "ents_p":0.9632461041,
    "ents_r":0.9826034793,
    "ents_per_type":{
      "Degree":{
        "p":0.9801587302,
        "r":0.9899799599,
        "f":0.9850448654
      },
      "Designation":{
        "p":0.9822587624,
        "r":0.9856708641,
        "f":0.9839618552
      },
      "Years":{
        "p":0.8737201365,
        "r":0.962406015,
        "f":0.915921288
      }
    },
    "transformer_loss":293.8719195203,
    "ner_loss":393.6294436094
  }
}